manim_table/__init__.py
manim_table/cell.py
manim_table/row.py
manim_table/table.py
manim_table-1.1.1.dist-info/METADATA
manim_table-1.1.1.dist-info/WHEEL
manim_table-1.1.1.dist-info/RECORD
