Metadata-Version: 2.4
Name: manim-table
Version: 1.1.1
Summary: 
Author: phil.oger@gmail.com
Requires-Python: >=3.12
Classifier: Programming Language :: Python :: 3
Classifier: Programming Language :: Python :: 3.12
Classifier: Programming Language :: Python :: 3.13
Classifier: Programming Language :: Python :: 3.14
Requires-Dist: manimgl (>=1.7.2,<2.0.0)
Requires-Dist: setuptools
